rtl/fc1_neuron.v
module fc1_neuron #(
    parameter INPUT_SIZE = 20
)(
    input clk,
    input rst,
    input start,

    input signed [7:0] input_data [0:INPUT_SIZE-1],
    input signed [7:0] weight_data [0:INPUT_SIZE-1],
    input signed [7:0] bias,

    output reg signed [31:0] out,
    output reg done
);

reg [5:0] index;
reg signed [31:0] acc;
reg running;

always @(posedge clk) begin
    if (rst) begin
        index   <= 0;
        acc     <= 0;
        done    <= 0;
        running <= 0;
        out     <= 0;
    end
    else begin

        // start pulse
        if (start && !running) begin
            index   <= 0;
            acc     <= 0;
            done    <= 0;
            running <= 1;
        end

        // accumulate
        if (running) begin
            acc <= acc + input_data[index] * weight_data[index];
            index <= index + 1;

            if (index == INPUT_SIZE-1) begin
                out <= acc + input_data[index] * weight_data[index] + bias;
                done <= 1;
                running <= 0;
            end
        end

    end
end

endmodule

sim/tb_fc1.v
`timescale 1ns/1ps

module tb_fc1;

reg clk = 0;
reg rst = 1;
reg start = 0;

wire done;
wire signed [31:0] out;

// clock
always #5 clk = ~clk;

// -------- input + weights ----------
reg signed [7:0] input_data [0:19];
reg signed [7:0] weight_data [0:19];
reg signed [7:0] bias;

// DUT
fc1_neuron dut(
    .clk(clk),
    .rst(rst),
    .start(start),
    .input_data(input_data),
    .weight_data(weight_data),
    .bias(bias),
    .out(out),
    .done(done)
);

integer i;

initial begin
    $dumpfile("sim/fc1.vcd");
    $dumpvars(0, tb_fc1);

    // load sample MFCC input (dummy for now)
    for(i=0;i<20;i=i+1)
        input_data[i] = i;

    // load weights from file
    $readmemh("rtl_weights/w1_n0.txt", weight_data);
    $display("First weight = %h", weight_data[0]);
    $display("Second weight = %h", weight_data[1]);
    $display("Third weight = %h", weight_data[2]);
    for (i=0; i<20; i=i+1) begin
    $display("RTL weight[%0d] = %0d", i, weight_data[i]);
    end


    bias = 0;

    #20 rst = 0;
    #10 start = 1;
    #10 start = 0;
    #200;

    $display("Neuron output = %d", out);

    $finish;
end

endmodule

sim/fc1.vcd
$date
	Wed Feb 25 23:14:40 2026
$end
$version
	Icarus Verilog
$end
$timescale
	1ps
$end
$scope module tb_fc1 $end
$var wire 32 ! out [31:0] $end
$var wire 1 " done $end
$var reg 8 # bias [7:0] $end
$var reg 1 $ clk $end
$var reg 1 % rst $end
$var reg 1 & start $end
$var integer 32 ' i [31:0] $end
$scope module dut $end
$var wire 8 ( bias [7:0] $end
$var wire 1 $ clk $end
$var wire 1 % rst $end
$var wire 1 & start $end
$var parameter 32 ) INPUT_SIZE $end
$var reg 32 * acc [31:0] $end
$var reg 1 " done $end
$var reg 6 + index [5:0] $end
$var reg 32 , out [31:0] $end
$var reg 1 - running $end
$upscope $end
$upscope $end
$enddefinitions $end
$comment Show the parameter values. $end
$dumpall
b10100 )
$end
#0
$dumpvars
x-
bx ,
bx +
bx *
b0 (
b10100 '
0&
1%
0$
b0 #
x"
bx !
$end
#5000
b0 !
b0 ,
0-
0"
b0 *
b0 +
1$
#10000
0$
#15000
1$
#20000
0$
0%
#25000
1$
#30000
0$
1&
#35000
1-
1$
#40000
0$
0&
#45000
b1 +
1$
#50000
0$
#55000
b10 +
b110 *
1$
#60000
0$
#65000
b11 +
b11111111111111111111111111111100 *
1$
#70000
0$
#75000
b100 +
b11111111111111111111111110010110 *
1$
#80000
0$
#85000
b101 +
b111110 *
1$
#90000
0$
#95000
b110 +
b1111111 *
1$
#100000
0$
#105000
b111 +
b110111 *
1$
#110000
0$
#115000
b1000 +
b100011110 *
1$
#120000
0$
#125000
b1001 +
b1101110 *
1$
#130000
0$
#135000
b1010 +
b1000010101 *
1$
#140000
0$
#145000
b1011 +
b1011010011 *
1$
#150000
0$
#155000
b1100 +
b1101111000 *
1$
#160000
0$
#165000
b1101 +
b1110010000 *
1$
#170000
0$
#175000
b1110 +
b1110110111 *
1$
#180000
0$
#185000
b1111 +
b11010011101 *
1$
#190000
0$
#195000
b10000 +
b1101100100 *
1$
#200000
0$
#205000
b10001 +
b10011010100 *
1$
#210000
0$
#215000
b10010 +
b11110011110 *
1$
#220000
0$
#225000
b10011 +
b11011111100 *
1$
#230000
0$
#235000
0-
1"
b10110100110 !
b10110100110 ,
b10100 +
b10110100110 *
1$
