rtl/fc1_neuron.v
module fc1_neuron #(
    parameter INPUT_SIZE = 20
)(
    input clk,
    input rst,
    input start,

    input signed [7:0] input_data [0:INPUT_SIZE-1],
    input signed [7:0] weight_data [0:INPUT_SIZE-1],
    input signed [7:0] bias,

    output reg signed [31:0] out,
    output reg done
);

reg [5:0] index;
reg signed [31:0] acc;
reg running;

always @(posedge clk) begin
    if (rst) begin
        index   <= 0;
        acc     <= 0;
        done    <= 0;
        running <= 0;
        out     <= 0;
    end
    else begin

        // start pulse
        if (start && !running) begin
            index   <= 0;
            acc     <= 0;
            done    <= 0;
            running <= 1;
        end

        // accumulate
        if (running) begin
            acc <= acc + input_data[index] * weight_data[index];
            index <= index + 1;

            if (index == INPUT_SIZE-1) begin
                out <= acc + input_data[index] * weight_data[index] + bias;
                done <= 1;
                running <= 0;
            end
        end

    end
end

endmodule

rtl/fc1_layer.v
module fc1_layer(
    input clk,
    input rst,
    input start,

    input signed [7:0] input_data [0:19],
    input signed [7:0] weights [0:319],  // 20x16 flattened
    input signed [7:0] bias [0:15],

    output reg signed [31:0] out [0:15],
    output reg done
);

reg [4:0] neuron_idx;
reg neuron_start;
wire neuron_done;
reg prev_done;
wire signed [31:0] neuron_out;

reg signed [7:0] neuron_weights [0:19];

// instantiate single neuron
fc1_neuron neuron(
    .clk(clk),
    .rst(rst),
    .start(neuron_start),
    .input_data(input_data),
    .weight_data(neuron_weights),
    .bias(bias[neuron_idx]),
    .out(neuron_out),
    .done(neuron_done)
);

integer i;

// always @(posedge clk) begin
//     if (rst) begin
//         neuron_idx <= 0;
//         done <= 0;
//         neuron_start <= 0;
//     end
//     else begin
//         if (start && neuron_idx == 0)
//             neuron_start <= 1;

//         if (neuron_start)
//             neuron_start <= 0;

//         if (neuron_done) begin
//             out[neuron_idx] <= neuron_out;
//             neuron_idx <= neuron_idx + 1;

//             if (neuron_idx == 15) begin
//                 done <= 1;
//             end
//             else begin
//                 neuron_start <= 1;
//             end
//         end
//     end
// end

always @(posedge clk) begin
    if (rst) begin
        neuron_idx <= 0;
        done <= 0;
        neuron_start <= 0;
        prev_done <= 0;
    end
    else begin

        prev_done <= neuron_done;

        if (start && neuron_idx == 0)
            neuron_start <= 1;

        if (neuron_start)
            neuron_start <= 0;

        // detect rising edge
        if (neuron_done && !prev_done) begin
            out[neuron_idx] <= neuron_out;
            neuron_idx <= neuron_idx + 1;

            if (neuron_idx == 15) begin
                done <= 1;
            end
            else begin
                neuron_start <= 1;
            end
        end
    end
end


// load weights for current neuron
always @(*) begin
    for (i=0;i<20;i=i+1) begin
        neuron_weights[i] = weights[neuron_idx*20 + i];
    end
end

endmodule

sim/tb_fc1_layer.v
`timescale 1ns/1ps

module tb_fc1_layer;

reg clk = 0;
reg rst = 1;
reg start = 0;

always #5 clk = ~clk;

wire done;

reg signed [7:0] input_data [0:19];
reg signed [7:0] weights [0:319];
reg signed [7:0] bias [0:15];

wire signed [31:0] out [0:15];

fc1_layer dut(
    .clk(clk),
    .rst(rst),
    .start(start),
    .input_data(input_data),
    .weights(weights),
    .bias(bias),
    .out(out),
    .done(done)
);

integer i;

initial begin
    $dumpfile("sim/fc1_layer.vcd");
    $dumpvars(0, tb_fc1_layer);

    // simple input (same as before)
    for(i=0;i<20;i=i+1)
        input_data[i] = i;

    // load weights
    $readmemh("rtl_weights/w1.txt", weights);

    // zero bias for now
    for(i=0;i<16;i=i+1)
        bias[i] = 0;

    #20 rst = 0;

    #10 start = 1;
    #10 start = 0;

    wait(done);

    $display("FC1 outputs:");
    for(i=0;i<16;i=i+1)
        $display("out[%0d] = %d", i, out[i]);

    #20 $finish;
end

endmodule

sim/fc1_layer.vcd
$date
	Thu Feb 26 23:22:24 2026
$end
$version
	Icarus Verilog
$end
$timescale
	1ps
$end
$scope module tb_fc1_layer $end
$var wire 1 ! done $end
$var reg 1 " clk $end
$var reg 1 # rst $end
$var reg 1 $ start $end
$var integer 32 % i [31:0] $end
$scope module dut $end
$var wire 1 " clk $end
$var wire 1 # rst $end
$var wire 1 $ start $end
$var wire 32 & neuron_out [31:0] $end
$var wire 1 ' neuron_done $end
$var reg 1 ! done $end
$var reg 5 ( neuron_idx [4:0] $end
$var reg 1 ) neuron_start $end
$var reg 1 * prev_done $end
$var integer 32 + i [31:0] $end
$scope module neuron $end
$var wire 8 , bias [7:0] $end
$var wire 1 " clk $end
$var wire 1 # rst $end
$var wire 1 ) start $end
$var parameter 32 - INPUT_SIZE $end
$var reg 32 . acc [31:0] $end
$var reg 1 ' done $end
$var reg 6 / index [5:0] $end
$var reg 32 0 out [31:0] $end
$var reg 1 1 running $end
$upscope $end
$upscope $end
$upscope $end
$enddefinitions $end
$comment Show the parameter values. $end
$dumpall
b10100 -
$end
#0
$dumpvars
x1
bx 0
bx /
bx .
bx ,
b10100 +
x*
x)
bx (
x'
bx &
b10000 %
0$
1#
0"
x!
$end
#5000
b10100 +
b0 &
b0 0
01
0'
b0 .
b0 /
0*
0)
0!
b0 ,
b0 (
1"
#10000
0"
#15000
1"
#20000
0"
0#
#25000
1"
#30000
0"
1$
#35000
1)
1"
#40000
0"
0$
#45000
11
0)
1"
#50000
0"
#55000
b1 /
1"
#60000
0"
#65000
b10 /
b11111111111111111111111111110000 .
1"
#70000
0"
#75000
b11 /
b111100 .
1"
#80000
0"
#85000
b100 /
b10000001 .
1"
#90000
0"
#95000
b101 /
b11101 .
1"
#100000
0"
#105000
b110 /
b11111111111111111111111111111111 .
1"
#110000
0"
#115000
b111 /
b101 .
1"
#120000
0"
#125000
b1000 /
b110110 .
1"
#130000
0"
#135000
b1001 /
b1001110 .
1"
#140000
0"
#145000
b1010 /
b1000101 .
1"
#150000
0"
#155000
b1011 /
b10001011 .
1"
#160000
0"
#165000
b1100 /
b11111111111111111111111110011001 .
1"
#170000
0"
#175000
b1101 /
b1011001 .
1"
#180000
0"
#185000
b1110 /
b1001111011 .
1"
#190000
0"
#195000
b1111 /
b10011 .
1"
#200000
0"
#205000
b10000 /
b10011010 .
1"
#210000
0"
#215000
b10001 /
b11111010 .
1"
#220000
0"
#225000
b10010 /
b11111111111111111111111001100011 .
1"
#230000
0"
#235000
b10011 /
b11111111111111111111110100011111 .
1"
#240000
0"
#245000
01
1'
b11111111111111111111101101010111 &
b11111111111111111111101101010111 0
b10100 /
b11111111111111111111101101010111 .
1"
#250000
0"
#255000
b10100 +
1)
b1 (
1*
1"
#260000
0"
#265000
11
0'
b0 .
b0 /
0)
1"
#270000
0"
#275000
0*
b1 /
1"
#280000
0"
#285000
b10 /
b10101 .
1"
#290000
0"
#295000
b11 /
b1101 .
1"
#300000
0"
#305000
b100 /
b11111111111111111111111111110010 .
1"
#310000
0"
#315000
b101 /
b11111111111111111111111111001110 .
1"
#320000
0"
#325000
b110 /
b11111111111111111111111111100010 .
1"
#330000
0"
#335000
b111 /
b0 .
1"
#340000
0"
#345000
b1000 /
b11111111111111111111111100101110 .
1"
#350000
0"
#355000
b1001 /
b11111111111111111111111101100110 .
1"
#360000
0"
#365000
b1010 /
b11111111111111111111111011010110 .
1"
#370000
0"
#375000
b1011 /
b11111111111111111111111011111110 .
1"
#380000
0"
#385000
b1100 /
b11111000 .
1"
#390000
0"
#395000
b1101 /
b10111100 .
1"
#400000
0"
#405000
b1110 /
b110100110 .
1"
#410000
0"
#415000
b1111 /
b1111001000 .
1"
#420000
0"
#425000
b10000 /
b1111110101 .
1"
#430000
0"
#435000
b10001 /
b111000101 .
1"
#440000
0"
#445000
b10010 /
b1000111100 .
1"
#450000
0"
#455000
b10011 /
b1010010110 .
1"
#460000
0"
#465000
01
1'
b111111110 &
b111111110 0
b10100 /
b111111110 .
1"
#470000
0"
#475000
b10100 +
1)
b10 (
1*
1"
#480000
0"
#485000
11
0'
b0 .
b0 /
0)
1"
#490000
0"
#495000
0*
b1 /
1"
#500000
0"
#505000
b10 /
b101110 .
1"
#510000
0"
#515000
b11 /
b1001010 .
1"
#520000
0"
#525000
b100 /
b11111111111111111111111111001111 .
1"
#530000
0"
#535000
b101 /
b11111111111111111111111101010111 .
1"
#540000
0"
#545000
b110 /
b11111111111111111111111011111000 .
1"
#550000
0"
#555000
b111 /
b11111111111111111111111000100110 .
1"
#560000
0"
#565000
b1000 /
b11111111111111111111111001111010 .
1"
#570000
0"
#575000
b1001 /
b11111111111111111111110101101010 .
1"
#580000
0"
#585000
b1010 /
b11111111111111111111110011110101 .
1"
#590000
0"
#595000
b1011 /
b11111111111111111111111001110001 .
1"
#600000
0"
#605000
b1100 /
b1100000 .
1"
#610000
0"
#615000
b1101 /
b11111111111111111111111011010100 .
1"
#620000
0"
#625000
b1110 /
b11111111111111111111110011011001 .
1"
#630000
0"
#635000
b1111 /
b11111111111111111111110011110101 .
1"
#640000
0"
#645000
b10000 /
b11111111111111111111110000010100 .
1"
#650000
0"
#655000
b10001 /
1"
#660000
0"
#665000
b10010 /
b11111111111111111111101111010000 .
1"
#670000
0"
#675000
b10011 /
b11111111111111111111110111011010 .
1"
#680000
0"
#685000
01
1'
b11111111111111111111110100001001 &
b11111111111111111111110100001001 0
b10100 /
b11111111111111111111110100001001 .
1"
#690000
0"
#695000
b10100 +
1)
b11 (
1*
1"
#700000
0"
#705000
11
0'
b0 .
b0 /
0)
1"
#710000
0"
#715000
0*
b1 /
1"
#720000
0"
#725000
b10 /
b11111111111111111111111111011011 .
1"
#730000
0"
#735000
b11 /
b11111111111111111111111111011111 .
1"
#740000
0"
#745000
b100 /
b0 .
1"
#750000
0"
#755000
b101 /
b10101000 .
1"
#760000
0"
#765000
b110 /
b100011011 .
1"
#770000
0"
#775000
b111 /
b110001 .
1"
#780000
0"
#785000
b1000 /
b101110011 .
1"
#790000
0"
#795000
b1001 /
b110110011 .
1"
#800000
0"
#805000
b1010 /
b101110100 .
1"
#810000
0"
#815000
b1011 /
b110010010 .
1"
#820000
0"
#825000
b1100 /
b1001001101 .
1"
#830000
0"
#835000
b1101 /
1"
#840000
0"
#845000
b1110 /
b1001000000 .
1"
#850000
0"
#855000
b1111 /
b111000010 .
1"
#860000
0"
#865000
b10000 /
b11111111111111111111111100111101 .
1"
#870000
0"
#875000
b10001 /
b11111111111111111111111011101101 .
1"
#880000
0"
#885000
b10010 /
b11111111111111111111101111110000 .
1"
#890000
0"
#895000
b10011 /
b11111111111111111111111001100110 .
1"
#900000
0"
#905000
01
1'
b1010100 &
b1010100 0
b10100 /
b1010100 .
1"
#910000
0"
#915000
b10100 +
1)
b100 (
1*
1"
#920000
0"
#925000
11
0'
b0 .
b0 /
0)
1"
#930000
0"
#935000
0*
b1 /
1"
#940000
0"
#945000
b10 /
b11111111111111111111111111110011 .
1"
#950000
0"
#955000
b11 /
b11111111111111111111111110011101 .
1"
#960000
0"
#965000
b100 /
b11111111111111111111111100011100 .
1"
#970000
0"
#975000
b101 /
b11111111111111111111111110101000 .
1"
#980000
0"
#985000
b110 /
b10001 .
1"
#990000
0"
#995000
b111 /
b101 .
1"
#1000000
0"
#1005000
b1000 /
b11111111111111111111111111111110 .
1"
#1010000
0"
#1015000
b1001 /
1"
#1020000
0"
#1025000
b1010 /
b111101 .
1"
#1030000
0"
#1035000
b1011 /
b110011011 .
1"
#1040000
0"
#1045000
b1100 /
b100100010 .
1"
#1050000
0"
#1055000
b1101 /
b1000011110 .
1"
#1060000
0"
#1065000
b1110 /
b1111011000 .
1"
#1070000
0"
#1075000
b1111 /
b10001100100 .
1"
#1080000
0"
#1085000
b10000 /
b11101000011 .
1"
#1090000
0"
#1095000
b10001 /
b11010000011 .
1"
#1100000
0"
#1105000
b10010 /
b101110111 .
1"
#1110000
0"
#1115000
b10011 /
b110001001 .
1"
#1120000
0"
#1125000
01
1'
b1111101001 &
b1111101001 0
b10100 /
b1111101001 .
1"
#1130000
0"
#1135000
b10100 +
1)
b101 (
1*
1"
#1140000
0"
#1145000
11
0'
b0 .
b0 /
0)
1"
#1150000
0"
#1155000
0*
b1 /
1"
#1160000
0"
#1165000
b10 /
b1110 .
1"
#1170000
0"
#1175000
b11 /
b10010 .
1"
#1180000
0"
#1185000
b100 /
b11000 .
1"
#1190000
0"
#1195000
b101 /
1"
#1200000
0"
#1205000
b110 /
b11111111111111111111111111111111 .
1"
#1210000
0"
#1215000
b111 /
b11111111111111111111111011000001 .
1"
#1220000
0"
#1225000
b1000 /
b11111111111111111111111101100010 .
1"
#1230000
0"
#1235000
b1001 /
b110010 .
1"
#1240000
0"
#1245000
b1010 /
b11111111111111111111111100111111 .
1"
#1250000
0"
#1255000
b1011 /
b100110011 .
1"
#1260000
0"
#1265000
b1100 /
b1001100111 .
1"
#1270000
0"
#1275000
b1101 /
b1111110011 .
1"
#1280000
0"
#1285000
b1110 /
b1010111011 .
1"
#1290000
0"
#1295000
b1111 /
b1000000101 .
1"
#1300000
0"
#1305000
b10000 /
b110001101 .
1"
#1310000
0"
#1315000
b10001 /
b111011101 .
1"
#1320000
0"
#1325000
b10010 /
b10110000100 .
1"
#1330000
0"
#1335000
b10011 /
b10101100000 .
1"
#1340000
0"
#1345000
01
1'
b1111010001 &
b1111010001 0
b10100 /
b1111010001 .
1"
#1350000
0"
#1355000
b10100 +
1)
b110 (
1*
1"
#1360000
0"
#1365000
11
0'
b0 .
b0 /
0)
1"
#1370000
0"
#1375000
0*
b1 /
1"
#1380000
0"
#1385000
b10 /
b1011 .
1"
#1390000
0"
#1395000
b11 /
b1110001 .
1"
#1400000
0"
#1405000
b100 /
b10011110 .
1"
#1410000
0"
#1415000
b101 /
b101001010 .
1"
#1420000
0"
#1425000
b110 /
b101110010 .
1"
#1430000
0"
#1435000
b111 /
b1011110 .
1"
#1440000
0"
#1445000
b1000 /
b10000001 .
1"
#1450000
0"
#1455000
b1001 /
b11111111111111111111111111010001 .
1"
#1460000
0"
#1465000
b1010 /
b11111111111111111111111110001001 .
1"
#1470000
0"
#1475000
b1011 /
b11111111111111111111111100101111 .
1"
#1480000
0"
#1485000
b1100 /
b0 .
1"
#1490000
0"
#1495000
b1101 /
b11111111111111111111111010000000 .
1"
#1500000
0"
#1505000
b1110 /
1"
#1510000
0"
#1515000
b1111 /
b11111111111111111111111010001110 .
1"
#1520000
0"
#1525000
b10000 /
b11111111111111111111111111001001 .
1"
#1530000
0"
#1535000
b10001 /
1"
#1540000
0"
#1545000
b10010 /
b1111111000 .
1"
#1550000
0"
#1555000
b10011 /
b110010100 .
1"
#1560000
0"
#1565000
01
1'
b11000011 &
b11000011 0
b10100 /
b11000011 .
1"
#1570000
0"
#1575000
b10100 +
1)
b111 (
1*
1"
#1580000
0"
#1585000
11
0'
b0 .
b0 /
0)
1"
#1590000
0"
#1595000
0*
b1 /
1"
#1600000
0"
#1605000
b10 /
b11111111111111111111111111100111 .
1"
#1610000
0"
#1615000
b11 /
b10001 .
1"
#1620000
0"
#1625000
b100 /
b11111111111111111111111110111010 .
1"
#1630000
0"
#1635000
b101 /
b1110110 .
1"
#1640000
0"
#1645000
b110 /
b11111111111111111111111101011001 .
1"
#1650000
0"
#1655000
b111 /
b11111111111111111111111101000111 .
1"
#1660000
0"
#1665000
b1000 /
b11111111111111111111111001010010 .
1"
#1670000
0"
#1675000
b1001 /
b11111111111111111111111101000010 .
1"
#1680000
0"
#1685000
b1010 /
b11101001 .
1"
#1690000
0"
#1695000
b1011 /
1"
#1700000
0"
#1705000
b1100 /
b100101011 .
1"
#1710000
0"
#1715000
b1101 /
1"
#1720000
0"
#1725000
b1110 /
b1000111100 .
1"
#1730000
0"
#1735000
b1111 /
b11111111111111111111111111010100 .
1"
#1740000
0"
#1745000
b10000 /
b11111111111111111111110100010011 .
1"
#1750000
0"
#1755000
b10001 /
b11111111111111111111110110110011 .
1"
#1760000
0"
#1765000
b10010 /
b101001001 .
1"
#1770000
0"
#1775000
b10011 /
b10101001011 .
1"
#1780000
0"
#1785000
01
1'
b1011011000 &
b1011011000 0
b10100 /
b1011011000 .
1"
#1790000
0"
#1795000
b10100 +
1)
b1000 (
1*
1"
#1800000
0"
#1805000
11
0'
b0 .
b0 /
0)
1"
#1810000
0"
#1815000
0*
b1 /
1"
#1820000
0"
#1825000
b10 /
b11111111111111111111111110110100 .
1"
#1830000
0"
#1835000
b11 /
b1000 .
1"
#1840000
0"
#1845000
b100 /
b11111111111111111111111111001001 .
1"
#1850000
0"
#1855000
b101 /
b1010001 .
1"
#1860000
0"
#1865000
b110 /
b11011101 .
1"
#1870000
0"
#1875000
b111 /
b11101001 .
1"
#1880000
0"
#1885000
b1000 /
b100010011 .
1"
#1890000
0"
#1895000
b1001 /
1"
#1900000
0"
#1905000
b1010 /
b11111111111111111111111111100001 .
1"
#1910000
0"
#1915000
b1011 /
b1001 .
1"
#1920000
0"
#1925000
b1100 /
b11111111111111111111111011101011 .
1"
#1930000
0"
#1935000
b1101 /
b11111111111111111111110111101111 .
1"
#1940000
0"
#1945000
b1110 /
b11111111111111111111110101010011 .
1"
#1950000
0"
#1955000
b1111 /
b11111111111111111111110001110011 .
1"
#1960000
0"
#1965000
b10000 /
b1010011010 .
1"
#1970000
0"
#1975000
b10001 /
b1110001010 .
1"
#1980000
0"
#1985000
b10010 /
b11111111111111111111111011000010 .
1"
#1990000
0"
#1995000
b10011 /
b11111111111111111111110010111000 .
1"
#2000000
0"
#2005000
01
1'
b11111111111111111111101110011011 &
b11111111111111111111101110011011 0
b10100 /
b11111111111111111111101110011011 .
1"
#2010000
0"
#2015000
b10100 +
1)
b1001 (
1*
1"
#2020000
0"
#2025000
11
0'
b0 .
b0 /
0)
1"
#2030000
0"
#2035000
0*
b1 /
1"
#2040000
0"
#2045000
b10 /
b111001 .
1"
#2050000
0"
#2055000
b11 /
b111101 .
1"
#2060000
0"
#2065000
b100 /
b101110 .
1"
#2070000
0"
#2075000
b101 /
1"
#2080000
0"
#2085000
b110 /
b11111111111111111111111101110000 .
1"
#2090000
0"
#2095000
b111 /
b11111111111111111111111011010100 .
1"
#2100000
0"
#2105000
b1000 /
b11111111111111111111110110010010 .
1"
#2110000
0"
#2115000
b1001 /
b11111111111111111111110111011010 .
1"
#2120000
0"
#2125000
b1010 /
b11111111111111111111110001110010 .
1"
#2130000
0"
#2135000
b1011 /
b11111111111111111111110000100010 .
1"
#2140000
0"
#2145000
b1100 /
b11111111111111111111101001011111 .
1"
#2150000
0"
#2155000
b1101 /
b11111111111111111111101001110111 .
1"
#2160000
0"
#2165000
b1110 /
b11111111111111111111101110111100 .
1"
#2170000
0"
#2175000
b1111 /
b11111111111111111111100110110110 .
1"
#2180000
0"
#2185000
b10000 /
b11111111111111111111100000000011 .
1"
#2190000
0"
#2195000
b10001 /
b11111111111111111111100010010011 .
1"
#2200000
0"
#2205000
b10010 /
b11111111111111111111100011000110 .
1"
#2210000
0"
#2215000
b10011 /
b11111111111111111111100011011000 .
1"
#2220000
0"
#2225000
01
1'
b11111111111111111111100011111110 &
b11111111111111111111100011111110 0
b10100 /
b11111111111111111111100011111110 .
1"
#2230000
0"
#2235000
b10100 +
1)
b1010 (
1*
1"
#2240000
0"
#2245000
11
0'
b0 .
b0 /
0)
1"
#2250000
0"
#2255000
0*
b1 /
1"
#2260000
0"
#2265000
b10 /
b11111111111111111111111111111000 .
1"
#2270000
0"
#2275000
b11 /
b1000110 .
1"
#2280000
0"
#2285000
b100 /
b1010010 .
1"
#2290000
0"
#2295000
b101 /
b110110 .
1"
#2300000
0"
#2305000
b110 /
b11111111111111111111111100001010 .
1"
#2310000
0"
#2315000
b111 /
b11111111111111111111111100110100 .
1"
#2320000
0"
#2325000
b1000 /
b11111111111111111111111001000110 .
1"
#2330000
0"
#2335000
b1001 /
b11111111111111111111111001011110 .
1"
#2340000
0"
#2345000
b1010 /
b11111111111111111111101111000100 .
1"
#2350000
0"
#2355000
b1011 /
b11111111111111111111110000110010 .
1"
#2360000
0"
#2365000
b1100 /
b11111111111111111111101011110011 .
1"
#2370000
0"
#2375000
b1101 /
b11111111111111111111101010010011 .
1"
#2380000
0"
#2385000
b1110 /
b11111111111111111111101101010110 .
1"
#2390000
0"
#2395000
b1111 /
b11111111111111111111101101110010 .
1"
#2400000
0"
#2405000
b10000 /
b11111111111111111111101111011011 .
1"
#2410000
0"
#2415000
b10001 /
1"
#2420000
0"
#2425000
b10010 /
b11111111111111111111101100001111 .
1"
#2430000
0"
#2435000
b10011 /
b11111111111111111111100101011111 .
1"
#2440000
0"
#2445000
01
1'
b11111111111111111111101010110101 &
b11111111111111111111101010110101 0
b10100 /
b11111111111111111111101010110101 .
1"
#2450000
0"
#2455000
b10100 +
1)
b1011 (
1*
1"
#2460000
0"
#2465000
11
0'
b0 .
b0 /
0)
1"
#2470000
0"
#2475000
0*
b1 /
1"
#2480000
0"
#2485000
b10 /
b11111111111111111111111111101011 .
1"
#2490000
0"
#2495000
b11 /
b1100001 .
1"
#2500000
0"
#2505000
b100 /
b1011011 .
1"
#2510000
0"
#2515000
b101 /
b100101111 .
1"
#2520000
0"
#2525000
b110 /
b11100100 .
1"
#2530000
0"
#2535000
b111 /
b100010100 .
1"
#2540000
0"
#2545000
b1000 /
b1111010 .
1"
#2550000
0"
#2555000
b1001 /
b111011010 .
1"
#2560000
0"
#2565000
b1010 /
b1011110001 .
1"
#2570000
0"
#2575000
b1011 /
b1011100111 .
1"
#2580000
0"
#2585000
b1100 /
b1100001000 .
1"
#2590000
0"
#2595000
b1101 /
1"
#2600000
0"
#2605000
b1110 /
b11010100011 .
1"
#2610000
0"
#2615000
b1111 /
b11100000101 .
1"
#2620000
0"
#2625000
b10000 /
b100100000011 .
1"
#2630000
0"
#2635000
b10001 /
b11110010011 .
1"
#2640000
0"
#2645000
b10010 /
b11010100101 .
1"
#2650000
0"
#2655000
b10011 /
b100100011011 .
1"
#2660000
0"
#2665000
01
1'
b11011100001 &
b11011100001 0
b10100 /
b11011100001 .
1"
#2670000
0"
#2675000
b10100 +
1)
b1100 (
1*
1"
#2680000
0"
#2685000
11
0'
b0 .
b0 /
0)
1"
#2690000
0"
#2695000
0*
b1 /
1"
#2700000
0"
#2705000
b10 /
b11111111111111111111111111010100 .
1"
#2710000
0"
#2715000
b11 /
b11111111111111111111111111001110 .
1"
#2720000
0"
#2725000
b100 /
b1101 .
1"
#2730000
0"
#2735000
b101 /
b11111111111111111111111100100001 .
1"
#2740000
0"
#2745000
b110 /
b11111111111111111111111100111111 .
1"
#2750000
0"
#2755000
b111 /
1"
#2760000
0"
#2765000
b1000 /
b11111111111111111111111100010101 .
1"
#2770000
0"
#2775000
b1001 /
1"
#2780000
0"
#2785000
b1010 /
b1010010000 .
1"
#2790000
0"
#2795000
b1011 /
b110010110 .
1"
#2800000
0"
#2805000
b1100 /
b10100100 .
1"
#2810000
0"
#2815000
b1101 /
b11111111111111111111111000010000 .
1"
#2820000
0"
#2825000
b1110 /
b11111111111111111111101000011010 .
1"
#2830000
0"
#2835000
b1111 /
b11111111111111111111100011011000 .
1"
#2840000
0"
#2845000
b10000 /
b11111111111111111111011100010110 .
1"
#2850000
0"
#2855000
b10001 /
b11111111111111111111100010000110 .
1"
#2860000
0"
#2865000
b10010 /
b11111111111111111111011101000011 .
1"
#2870000
0"
#2875000
b10011 /
b11111111111111111111011011000101 .
1"
#2880000
0"
#2885000
01
1'
b11111111111111111111010111001110 &
b11111111111111111111010111001110 0
b10100 /
b11111111111111111111010111001110 .
1"
#2890000
0"
#2895000
b10100 +
1)
b1101 (
1*
1"
#2900000
0"
#2905000
11
0'
b0 .
b0 /
0)
1"
#2910000
0"
#2915000
0*
b1 /
1"
#2920000
0"
#2925000
b10 /
b11111111111111111111111111111110 .
1"
#2930000
0"
#2935000
b11 /
1"
#2940000
0"
#2945000
b100 /
b11111111111111111111111110110110 .
1"
#2950000
0"
#2955000
b101 /
1"
#2960000
0"
#2965000
b110 /
b11111111111111111111111100101111 .
1"
#2970000
0"
#2975000
b111 /
b11111111111111111111111101000001 .
1"
#2980000
0"
#2985000
b1000 /
b11111111111111111111111101001000 .
1"
#2990000
0"
#2995000
b1001 /
b11111111111111111111111010100000 .
1"
#3000000
0"
#3005000
b1010 /
b11111111111111111111111001001111 .
1"
#3010000
0"
#3015000
b1011 /
b11111111111111111111110110000111 .
1"
#3020000
0"
#3025000
b1100 /
b11111111111111111111101111001111 .
1"
#3030000
0"
#3035000
b1101 /
b11111111111111111111110111000111 .
1"
#3040000
0"
#3045000
b1110 /
b11111111111111111111110100101011 .
1"
#3050000
0"
#3055000
b1111 /
b11111111111111111111110011010111 .
1"
#3060000
0"
#3065000
b10000 /
1"
#3070000
0"
#3075000
b10001 /
b11111111111111111111111101000111 .
1"
#3080000
0"
#3085000
b10010 /
b1101000 .
1"
#3090000
0"
#3095000
b10011 /
b1111010 .
1"
#3100000
0"
#3105000
01
1'
b1001000010 &
b1001000010 0
b10100 /
b1001000010 .
1"
#3110000
0"
#3115000
b10100 +
1)
b1110 (
1*
1"
#3120000
0"
#3125000
11
0'
b0 .
b0 /
0)
1"
#3130000
0"
#3135000
0*
b1 /
1"
#3140000
0"
#3145000
b10 /
b11111111111111111111111110111101 .
1"
#3150000
0"
#3155000
b11 /
b1010101 .
1"
#3160000
0"
#3165000
b100 /
b11111111111111111111111110000000 .
1"
#3170000
0"
#3175000
b101 /
1"
#3180000
0"
#3185000
b110 /
b11111111111111111111111011010001 .
1"
#3190000
0"
#3195000
b111 /
b11111111111111111111111010100001 .
1"
#3200000
0"
#3205000
b1000 /
b11111111111111111111111000001110 .
1"
#3210000
0"
#3215000
b1001 /
b11111111111111111111110111000110 .
1"
#3220000
0"
#3225000
b1010 /
b11111111111111111111110001011110 .
1"
#3230000
0"
#3235000
b1011 /
b11111111111111111111110100111010 .
1"
#3240000
0"
#3245000
b1100 /
b11111111111111111111110101111100 .
1"
#3250000
0"
#3255000
b1101 /
b11111111111111111111110010110000 .
1"
#3260000
0"
#3265000
b1110 /
b11111111111111111111101100101010 .
1"
#3270000
0"
#3275000
b1111 /
b11111111111111111111101100111000 .
1"
#3280000
0"
#3285000
b10000 /
b11111111111111111111101100001011 .
1"
#3290000
0"
#3295000
b10001 /
1"
#3300000
0"
#3305000
b10010 /
b1000000100 .
1"
#3310000
0"
#3315000
b10011 /
b11111111111111111111111111010110 .
1"
#3320000
0"
#3325000
01
1'
b100101100 &
b100101100 0
b10100 /
b100101100 .
1"
#3330000
0"
#3335000
b10100 +
1)
b1111 (
1*
1"
#3340000
0"
#3345000
11
0'
b0 .
b0 /
0)
1"
#3350000
0"
#3355000
0*
b1 /
1"
#3360000
0"
#3365000
b10 /
b11111111111111111111111111011010 .
1"
#3370000
0"
#3375000
b11 /
b1001000 .
1"
#3380000
0"
#3385000
b100 /
b1110101 .
1"
#3390000
0"
#3395000
b101 /
b101101 .
1"
#3400000
0"
#3405000
b110 /
b1001101100 .
1"
#3410000
0"
#3415000
b111 /
b1000010010 .
1"
#3420000
0"
#3425000
b1000 /
b1010110011 .
1"
#3430000
0"
#3435000
b1001 /
b111001011 .
1"
#3440000
0"
#3445000
b1010 /
b1010100011 .
1"
#3450000
0"
#3455000
b1011 /
b1010101101 .
1"
#3460000
0"
#3465000
b1100 /
b111111101 .
1"
#3470000
0"
#3475000
b1101 /
1"
#3480000
0"
#3485000
b1110 /
b1000001010 .
1"
#3490000
0"
#3495000
b1111 /
b111100 .
1"
#3500000
0"
#3505000
b10000 /
b11111111111111111111111011010100 .
1"
#3510000
0"
#3515000
b10001 /
b11111111111111111111110100000100 .
1"
#3520000
0"
#3525000
b10010 /
b11111111111111111111100001101111 .
1"
#3530000
0"
#3535000
b10011 /
b11111111111111111111010010110101 .
1"
#3540000
0"
#3545000
01
1'
b11111111111111111111010100100111 &
b11111111111111111111010100100111 0
b10100 /
b11111111111111111111010100100111 .
1"
#3550000
0"
#3555000
b10000 %
b10100 +
1!
bx ,
b10000 (
1*
1"
