rtl/argmax2.v
module argmax2(
    input  signed [31:0] in0,
    input  signed [31:0] in1,
    output reg result
);

always @(*) begin
    if (in1 > in0)
        result = 1;   // drone
    else
        result = 0;   // non-drone
end

endmodule

rtl/fc1_neuron.v
module fc1_neuron #(
    parameter INPUT_SIZE = 20
)(
    input clk,
    input rst,
    input start,

    input signed [7:0] input_data [0:INPUT_SIZE-1],
    input signed [7:0] weight_data [0:INPUT_SIZE-1],
    input signed [7:0] bias,

    output reg signed [31:0] out,
    output reg done
);

reg [5:0] index;
reg signed [31:0] acc;
reg running;

always @(posedge clk) begin
    if (rst) begin
        index   <= 0;
        acc     <= 0;
        done    <= 0;
        running <= 0;
        out     <= 0;
    end
    else begin

        // start pulse
        if (start && !running) begin
            index   <= 0;
            acc     <= 0;
            done    <= 0;
            running <= 1;
        end

        // accumulate
        if (running) begin
            acc <= acc + input_data[index] * weight_data[index];
            index <= index + 1;

            if (index == INPUT_SIZE-1) begin
                out <= acc + input_data[index] * weight_data[index] + bias;
                done <= 1;
                running <= 0;
            end
        end

    end
end

endmodule

rtl/fc3_layer.v
module fc3_layer(
    input clk,
    input rst,
    input start,

    input signed [31:0] input_data [0:7],
    input signed [7:0] weights [0:15],   // 8x2
    input signed [7:0] bias [0:1],

    output reg signed [31:0] out [0:1],
    output reg done
);

reg [1:0] neuron_idx;
reg neuron_start;
wire neuron_done;
wire signed [31:0] neuron_out;

reg signed [7:0] neuron_weights [0:7];
reg signed [7:0] input8 [0:7];

integer k;
always @(*) begin
    for (k=0;k<8;k=k+1)
        input8[k] = input_data[k][7:0];
end

fc1_neuron #(.INPUT_SIZE(8)) neuron(
    .clk(clk),
    .rst(rst),
    .start(neuron_start),
    .input_data(input8),
    .weight_data(neuron_weights),
    .bias(bias[neuron_idx]),
    .out(neuron_out),
    .done(neuron_done)
);

integer i;
reg prev_done;

always @(posedge clk) begin
    if (rst) begin
        neuron_idx <= 0;
        done <= 0;
        neuron_start <= 0;
        prev_done <= 0;
    end
    else begin
        prev_done <= neuron_done;

        if (start && neuron_idx == 0)
            neuron_start <= 1;

        if (neuron_start)
            neuron_start <= 0;

        if (neuron_done && !prev_done) begin
            out[neuron_idx] <= neuron_out;
            neuron_idx <= neuron_idx + 1;

            if (neuron_idx == 1) begin
                done <= 1;
            end
            else begin
                neuron_start <= 1;
            end
        end
    end
end

always @(*) begin
    for (i=0;i<8;i=i+1)
        neuron_weights[i] = weights[neuron_idx*8 + i];
end

endmodule

rtl/relu8.v
module relu8(
    input  signed [31:0] in [0:7],
    output signed [31:0] out [0:7]
);

genvar i;
generate
    for (i=0; i<8; i=i+1) begin
        assign out[i] = (in[i] < 0) ? 0 : in[i];
    end
endgenerate

endmodule

rtl/fc2_layer.v
module fc2_layer(
    input clk,
    input rst,
    input start,

    input signed [31:0] input_data [0:15],
    input signed [7:0] weights [0:127],   // 16x8
    input signed [7:0] bias [0:7],

    output reg signed [31:0] out [0:7],
    output reg done
);

reg [3:0] neuron_idx;
reg neuron_start;
wire neuron_done;
wire signed [31:0] neuron_out;

reg signed [7:0] neuron_weights [0:15];
reg signed [7:0] input8 [0:15];

// convert 32-bit input to 8-bit
integer k;
always @(*) begin
    for (k=0;k<16;k=k+1)
        input8[k] = input_data[k][7:0];
end

fc1_neuron #(.INPUT_SIZE(16)) neuron(
    .clk(clk),
    .rst(rst),
    .start(neuron_start),
    .input_data(input8),
    .weight_data(neuron_weights),
    .bias(bias[neuron_idx]),
    .out(neuron_out),
    .done(neuron_done)
);

integer i;
reg prev_done;

always @(posedge clk) begin
    if (rst) begin
        neuron_idx <= 0;
        done <= 0;
        neuron_start <= 0;
        prev_done <= 0;
    end
    else begin
        prev_done <= neuron_done;

        if (start && neuron_idx == 0)
            neuron_start <= 1;

        if (neuron_start)
            neuron_start <= 0;

        if (neuron_done && !prev_done) begin
            out[neuron_idx] <= neuron_out;
            neuron_idx <= neuron_idx + 1;

            if (neuron_idx == 7) begin
                done <= 1;
            end
            else begin
                neuron_start <= 1;
            end
        end
    end
end

// load weights for current neuron
always @(*) begin
    for (i=0;i<16;i=i+1)
        neuron_weights[i] = weights[neuron_idx*16 + i];
end

endmodule

rtl/relu16.v
module relu16(
    input signed [31:0] in [0:15],
    output signed [31:0] out [0:15]
);

genvar i;
generate
    for (i=0; i<16; i=i+1) begin
        assign out[i] = (in[i] < 0) ? 0 : in[i];
    end
endgenerate

endmodule

rtl/fc1_layer.v
module fc1_layer(
    input clk,
    input rst,
    input start,

    input signed [7:0] input_data [0:19],
    input signed [7:0] weights [0:319],  // 20x16 flattened
    input signed [7:0] bias [0:15],

    output reg signed [31:0] out [0:15],
    output reg done
);

reg [4:0] neuron_idx;
reg neuron_start;
wire neuron_done;
reg prev_done;
wire signed [31:0] neuron_out;

reg signed [7:0] neuron_weights [0:19];

// instantiate single neuron
fc1_neuron neuron(
    .clk(clk),
    .rst(rst),
    .start(neuron_start),
    .input_data(input_data),
    .weight_data(neuron_weights),
    .bias(bias[neuron_idx]),
    .out(neuron_out),
    .done(neuron_done)
);

integer i;

// always @(posedge clk) begin
//     if (rst) begin
//         neuron_idx <= 0;
//         done <= 0;
//         neuron_start <= 0;
//     end
//     else begin
//         if (start && neuron_idx == 0)
//             neuron_start <= 1;

//         if (neuron_start)
//             neuron_start <= 0;

//         if (neuron_done) begin
//             out[neuron_idx] <= neuron_out;
//             neuron_idx <= neuron_idx + 1;

//             if (neuron_idx == 15) begin
//                 done <= 1;
//             end
//             else begin
//                 neuron_start <= 1;
//             end
//         end
//     end
// end

always @(posedge clk) begin
    if (rst) begin
        neuron_idx <= 0;
        done <= 0;
        neuron_start <= 0;
        prev_done <= 0;
    end
    else begin

        prev_done <= neuron_done;

        if (start && neuron_idx == 0)
            neuron_start <= 1;

        if (neuron_start)
            neuron_start <= 0;

        // detect rising edge
        if (neuron_done && !prev_done) begin
            out[neuron_idx] <= neuron_out;
            neuron_idx <= neuron_idx + 1;

            if (neuron_idx == 15) begin
                done <= 1;
            end
            else begin
                neuron_start <= 1;
            end
        end
    end
end


// load weights for current neuron
always @(*) begin
    for (i=0;i<20;i=i+1) begin
        neuron_weights[i] = weights[neuron_idx*20 + i];
    end
end

endmodule

rtl/top_nn.v
module top_nn(
    input clk,
    input rst,
    input start,

    input signed [7:0] input_data [0:19],

    input signed [7:0] w1 [0:319],
    input signed [7:0] b1 [0:15],

    input signed [7:0] w2 [0:127],
    input signed [7:0] b2 [0:7],

    input signed [7:0] w3 [0:15],
    input signed [7:0] b3 [0:1],

    output result,
    output done,

    output signed [31:0] drone_score,
    output signed [31:0] background_score
);

wire signed [31:0] fc1_out [0:15];
wire signed [31:0] relu1_out [0:15];

wire signed [31:0] fc2_out [0:7];
wire signed [31:0] relu2_out [0:7];

wire signed [31:0] fc3_out [0:1];

assign background_score = fc3_out[0];
assign drone_score = fc3_out[1];

wire fc1_done, fc2_done, fc3_done;

// FC1
fc1_layer fc1(
    .clk(clk),
    .rst(rst),
    .start(start),
    .input_data(input_data),
    .weights(w1),
    .bias(b1),
    .out(fc1_out),
    .done(fc1_done)
);

// ReLU1
relu16 r1(
    .in(fc1_out),
    .out(relu1_out)
);

// FC2
fc2_layer fc2(
    .clk(clk),
    .rst(rst),
    .start(fc1_done),
    .input_data(relu1_out),
    .weights(w2),
    .bias(b2),
    .out(fc2_out),
    .done(fc2_done)
);

// ReLU2
relu8 r2(
    .in(fc2_out),
    .out(relu2_out)
);

// FC3
fc3_layer fc3(
    .clk(clk),
    .rst(rst),
    .start(fc2_done),
    .input_data(relu2_out),
    .weights(w3),
    .bias(b3),
    .out(fc3_out),
    .done(fc3_done)
);

// Argmax
argmax2 am(
    .in0(fc3_out[0]),
    .in1(fc3_out[1]),
    .result(result)
);

assign done = fc3_done;

endmodule

sim/tb_top_nn.v
`timescale 1ns/1ps

module tb_top_nn;

integer cycle_count = 0;

reg clk = 0;
reg rst = 1;
reg start = 0;

always #5 clk = ~clk;

always @(posedge clk)
    cycle_count = cycle_count + 1;

wire done;
wire result;

wire signed [31:0] drone_score;
wire signed [31:0] background_score;

// ---------- INPUT ----------
reg signed [7:0] input_data [0:19];

// ---------- WEIGHTS ----------
reg signed [7:0] w1 [0:319];
reg signed [7:0] w2 [0:127];
reg signed [7:0] w3 [0:15];

reg signed [7:0] b1 [0:15];
reg signed [7:0] b2 [0:7];
reg signed [7:0] b3 [0:1];

// DUT
top_nn dut(
    .clk(clk),
    .rst(rst),
    .start(start),
    .input_data(input_data),
    .w1(w1),
    .b1(b1),
    .w2(w2),
    .b2(b2),
    .w3(w3),
    .b3(b3),
    .result(result),
    .done(done),
    .drone_score(drone_score),
    .background_score(background_score)
);

integer i;

initial begin
    $dumpfile("sim/top_nn.vcd");
    $dumpvars(0,tb_top_nn);

    // example MFCC input
    // for(i=0;i<20;i=i+1)
    //     input_data[i] = i;

    // load real MFCC feature vector
    $readmemh("rtl_weights/mfcc_input.txt", input_data);

    // load weights
    $readmemh("rtl_weights/w1.txt", w1);
    $readmemh("rtl_weights/w2.txt", w2);
    //$readmemh("rtl_weights/w3.txt", w3);
    $readmemh("rtl_weights/w3_fixed.txt", w3);


    // zero bias for now
    // for(i=0;i<16;i=i+1) b1[i]=0;
    // for(i=0;i<8;i=i+1)  b2[i]=0;
    // for(i=0;i<2;i=i+1)  b3[i]=0;

    $readmemh("rtl_weights/b1.txt", b1);
    $readmemh("rtl_weights/b2.txt", b2);
    //$readmemh("rtl_weights/b3.txt", b3);
    $readmemh("rtl_weights/b3_fixed.txt", b3);

    // #20 rst = 0;

    // #10 start = 1;
    // #10 start = 0;

    // wait(done);

    // $display("Total inference cycles = %d", cycle_count);

    // $display("Drone score      = %d", drone_score);
    // $display("Background score = %d", background_score);

    // if(result)
    //     $display("DRONE DETECTED");
    // else
    //     $display("NO DRONE");

    #20 rst = 0;

    repeat (5) begin

        // wait until previous inference finishes and done resets
        //@(negedge done);

        // reset accelerator
        rst = 1;
        #20;
        rst = 0;

        @(posedge clk);
        cycle_count = 0;

        // trigger inference
        #10 start = 1;
        #10 start = 0;

        // wait until inference finishes
        wait(done);
        //wait(done == 1);

        $display("Total inference cycles = %d", cycle_count);
        $display("Latency (us) = %f", cycle_count * 10.0 / 1000.0);
        $display("Throughput = %f inferences/sec", 100000000.0 / cycle_count);
        $display("Drone score      = %d", drone_score);
        $display("Background score = %d", background_score);

        if(result)
            $display("Decision = DRONE DETECTED");
        else
            $display("Decision = NO DRONE");

        #50;
    end

    #20 $finish;
end

endmodule

sim/top_nn.vcd
$date
	Sat Mar 07 21:10:22 2026
$end
$version
	Icarus Verilog
$end
$timescale
	1ps
$end
$scope module tb_top_nn $end
$var wire 1 ! result $end
$var wire 32 " drone_score [31:0] $end
$var wire 1 # done $end
$var wire 32 $ background_score [31:0] $end
$var reg 1 % clk $end
$var reg 1 & rst $end
$var reg 1 ' start $end
$var integer 32 ( cycle_count [31:0] $end
$scope module dut $end
$var wire 32 ) background_score [31:0] $end
$var wire 1 % clk $end
$var wire 1 # done $end
$var wire 32 * drone_score [31:0] $end
$var wire 1 & rst $end
$var wire 1 ' start $end
$var wire 1 ! result $end
$var wire 1 + fc3_done $end
$var wire 1 , fc2_done $end
$var wire 1 - fc1_done $end
$scope module am $end
$var wire 32 . in0 [31:0] $end
$var wire 32 / in1 [31:0] $end
$var reg 1 ! result $end
$upscope $end
$scope module fc1 $end
$var wire 1 % clk $end
$var wire 1 & rst $end
$var wire 1 ' start $end
$var wire 32 0 neuron_out [31:0] $end
$var wire 1 1 neuron_done $end
$var reg 1 - done $end
$var reg 5 2 neuron_idx [4:0] $end
$var reg 1 3 neuron_start $end
$var reg 1 4 prev_done $end
$var integer 32 5 i [31:0] $end
$scope module neuron $end
$var wire 8 6 bias [7:0] $end
$var wire 1 % clk $end
$var wire 1 & rst $end
$var wire 1 3 start $end
$var parameter 32 7 INPUT_SIZE $end
$var reg 32 8 acc [31:0] $end
$var reg 1 1 done $end
$var reg 6 9 index [5:0] $end
$var reg 32 : out [31:0] $end
$var reg 1 ; running $end
$upscope $end
$upscope $end
$scope module fc2 $end
$var wire 1 % clk $end
$var wire 1 & rst $end
$var wire 1 - start $end
$var wire 32 < neuron_out [31:0] $end
$var wire 1 = neuron_done $end
$var reg 1 , done $end
$var reg 4 > neuron_idx [3:0] $end
$var reg 1 ? neuron_start $end
$var reg 1 @ prev_done $end
$var integer 32 A i [31:0] $end
$var integer 32 B k [31:0] $end
$scope module neuron $end
$var wire 8 C bias [7:0] $end
$var wire 1 % clk $end
$var wire 1 & rst $end
$var wire 1 ? start $end
$var parameter 32 D INPUT_SIZE $end
$var reg 32 E acc [31:0] $end
$var reg 1 = done $end
$var reg 6 F index [5:0] $end
$var reg 32 G out [31:0] $end
$var reg 1 H running $end
$upscope $end
$upscope $end
$scope module fc3 $end
$var wire 1 % clk $end
$var wire 1 & rst $end
$var wire 1 , start $end
$var wire 32 I neuron_out [31:0] $end
$var wire 1 J neuron_done $end
$var reg 1 + done $end
$var reg 2 K neuron_idx [1:0] $end
$var reg 1 L neuron_start $end
$var reg 1 M prev_done $end
$var integer 32 N i [31:0] $end
$var integer 32 O k [31:0] $end
$scope module neuron $end
$var wire 8 P bias [7:0] $end
$var wire 1 % clk $end
$var wire 1 & rst $end
$var wire 1 L start $end
$var parameter 32 Q INPUT_SIZE $end
$var reg 32 R acc [31:0] $end
$var reg 1 J done $end
$var reg 6 S index [5:0] $end
$var reg 32 T out [31:0] $end
$var reg 1 U running $end
$upscope $end
$upscope $end
$scope module r1 $end
$scope begin genblk1[0] $end
$var parameter 2 V i $end
$upscope $end
$scope begin genblk1[1] $end
$var parameter 2 W i $end
$upscope $end
$scope begin genblk1[2] $end
$var parameter 3 X i $end
$upscope $end
$scope begin genblk1[3] $end
$var parameter 3 Y i $end
$upscope $end
$scope begin genblk1[4] $end
$var parameter 4 Z i $end
$upscope $end
$scope begin genblk1[5] $end
$var parameter 4 [ i $end
$upscope $end
$scope begin genblk1[6] $end
$var parameter 4 \ i $end
$upscope $end
$scope begin genblk1[7] $end
$var parameter 4 ] i $end
$upscope $end
$scope begin genblk1[8] $end
$var parameter 5 ^ i $end
$upscope $end
$scope begin genblk1[9] $end
$var parameter 5 _ i $end
$upscope $end
$scope begin genblk1[10] $end
$var parameter 5 ` i $end
$upscope $end
$scope begin genblk1[11] $end
$var parameter 5 a i $end
$upscope $end
$scope begin genblk1[12] $end
$var parameter 5 b i $end
$upscope $end
$scope begin genblk1[13] $end
$var parameter 5 c i $end
$upscope $end
$scope begin genblk1[14] $end
$var parameter 5 d i $end
$upscope $end
$scope begin genblk1[15] $end
$var parameter 5 e i $end
$upscope $end
$upscope $end
$scope module r2 $end
$scope begin genblk1[0] $end
$var parameter 2 f i $end
$upscope $end
$scope begin genblk1[1] $end
$var parameter 2 g i $end
$upscope $end
$scope begin genblk1[2] $end
$var parameter 3 h i $end
$upscope $end
$scope begin genblk1[3] $end
$var parameter 3 i i $end
$upscope $end
$scope begin genblk1[4] $end
$var parameter 4 j i $end
$upscope $end
$scope begin genblk1[5] $end
$var parameter 4 k i $end
$upscope $end
$scope begin genblk1[6] $end
$var parameter 4 l i $end
$upscope $end
$scope begin genblk1[7] $end
$var parameter 4 m i $end
$upscope $end
$upscope $end
$upscope $end
$upscope $end
$enddefinitions $end
$comment Show the parameter values. $end
$dumpall
b111 m
b110 l
b101 k
b100 j
b11 i
b10 h
b1 g
b0 f
b1111 e
b1110 d
b1101 c
b1100 b
b1011 a
b1010 `
b1001 _
b1000 ^
b111 ]
b110 \
b101 [
b100 Z
b11 Y
b10 X
b1 W
b0 V
b1000 Q
b10000 D
b10100 7
$end
#0
$dumpvars
xU
bx T
bx S
bx R
bx P
bx O
b1000 N
xM
xL
bx K
xJ
bx I
xH
bx G
bx F
bx E
bx C
bx B
b10000 A
x@
x?
bx >
x=
bx <
x;
bx :
bx 9
bx 8
bx 6
b10100 5
x4
x3
bx 2
x1
bx 0
bx /
bx .
x-
x,
x+
bx *
bx )
b0 (
0'
1&
0%
bx $
x#
bx "
x!
$end
#5000
b10100 5
b10000 A
b1000 N
b0 0
b0 :
0;
01
b0 8
b0 9
04
03
0-
b101011 6
b0 2
b0 <
b0 G
0H
0=
b0 E
b0 F
0@
0?
0,
b11100100 C
b0 >
b0 I
b0 T
0U
0J
b0 R
b0 S
0M
0L
0#
0+
b10111110 P
b0 K
b1 (
1%
#10000
0%
#15000
b10 (
1%
#20000
0%
1&
#25000
b11 (
1%
#30000
0%
#35000
b100 (
1%
#40000
0%
0&
#45000
b1 (
1%
#50000
0%
#55000
13
b10 (
1%
1'
#60000
0%
#65000
1;
03
b11 (
1%
0'
#70000
0%
#75000
b1 9
b11111111111111111111110110101000 8
b100 (
1%
#80000
0%
#85000
b10 9
b11111111111111111111100101110000 8
b101 (
1%
#90000
0%
#95000
b11 9
b11111111111111111111011000100010 8
b110 (
1%
#100000
0%
#105000
b100 9
b11111111111111111111101000111100 8
b111 (
1%
#110000
0%
#115000
b101 9
b11111111111111111111100111101000 8
b1000 (
1%
#120000
0%
#125000
b110 9
b11111111111111111111100010111000 8
b1001 (
1%
#130000
0%
#135000
b111 9
b11111111111111111111011110010010 8
b1010 (
1%
#140000
0%
#145000
b1000 9
b11111111111111111111100001100011 8
b1011 (
1%
#150000
0%
#155000
b1001 9
b11111111111111111111100010000011 8
b1100 (
1%
#160000
0%
#165000
b1010 9
b11111111111111111111100000001011 8
b1101 (
1%
#170000
0%
#175000
b1011 9
b1110 (
1%
#180000
0%
#185000
b1100 9
b11111111111111111111011111110110 8
b1111 (
1%
#190000
0%
#195000
b1101 9
b11111111111111111111100011011100 8
b10000 (
1%
#200000
0%
#205000
b1110 9
b11111111111111111111100000101000 8
b10001 (
1%
#210000
0%
#215000
b1111 9
b11111111111111111111100000001000 8
b10010 (
1%
#220000
0%
#225000
b10000 9
b11111111111111111111100000110101 8
b10011 (
1%
#230000
0%
#235000
b10001 9
b11111111111111111111011111000101 8
b10100 (
1%
#240000
0%
#245000
b10010 9
b11111111111111111111011110000011 8
b10101 (
1%
#250000
0%
#255000
b10011 9
b11111111111111111111100010010111 8
b10110 (
1%
#260000
0%
#265000
0;
11
b11111111111111111111100000110010 0
b11111111111111111111100000110010 :
b10100 9
b11111111111111111111100000000111 8
b10111 (
1%
#270000
0%
#275000
b10000 B
b10100 5
13
b11001010 6
b1 2
14
b11000 (
1%
#280000
0%
#285000
1;
01
b0 8
b0 9
03
b11001 (
1%
#290000
0%
#295000
04
b1 9
b11100001000 8
b11010 (
1%
#300000
0%
#305000
b10 9
b110010000000 8
b11011 (
1%
#310000
0%
#315000
b11 9
b101001000000 8
b11100 (
1%
#320000
0%
#325000
b100 9
b110100001010 8
b11101 (
1%
#330000
0%
#335000
b101 9
b110101010000 8
b11110 (
1%
#340000
0%
#345000
b110 9
b110100000100 8
b11111 (
1%
#350000
0%
#355000
b111 9
b110011101000 8
b100000 (
1%
#360000
0%
#365000
b1000 9
b101101110010 8
b100001 (
1%
#370000
0%
#375000
b1001 9
b100111010010 8
b100010 (
1%
#380000
0%
#385000
b1010 9
b101010000001 8
b100011 (
1%
#390000
0%
#395000
b1011 9
b100100 (
1%
#400000
0%
#405000
b1100 9
b101000000000 8
b100101 (
1%
#410000
0%
#415000
b1101 9
b101001100100 8
b100110 (
1%
#420000
0%
#425000
b1110 9
b101101000101 8
b100111 (
1%
#430000
0%
#435000
b1111 9
b101111100101 8
b101000 (
1%
#440000
0%
#445000
b10000 9
b101001010000 8
b101001 (
1%
#450000
0%
#455000
b10001 9
b101101000000 8
b101010 (
1%
#460000
0%
#465000
b10010 9
b101101000011 8
b101011 (
1%
#470000
0%
#475000
b10011 9
b101011001011 8
b101100 (
1%
#480000
0%
#485000
0;
11
b101010011011 0
b101010011011 :
b10100 9
b101011010001 8
b101101 (
1%
#490000
0%
#495000
b10000 B
b10100 5
13
b11 6
b10 2
14
b101110 (
1%
#500000
0%
#505000
1;
01
b0 8
b0 9
03
b101111 (
1%
#510000
0%
#515000
04
b1 9
b111111010010 8
b110000 (
1%
#520000
0%
#525000
b10 9
b101111000010 8
b110001 (
1%
#530000
0%
#535000
b11 9
b101111010100 8
b110010 (
1%
#540000
0%
#545000
b100 9
b100000111000 8
b110011 (
1%
#550000
0%
#555000
b101 9
b100011000100 8
b110100 (
1%
#560000
0%
#565000
b110 9
b10110100110 8
b110101 (
1%
#570000
0%
#575000
b111 9
b11100100000 8
b110110 (
1%
#580000
0%
#585000
b1000 9
b11111011011 8
b110111 (
1%
#590000
0%
#595000
b1001 9
b11101000011 8
b111000 (
1%
#600000
0%
#605000
b1010 9
b100000000001 8
b111001 (
1%
#610000
0%
#615000
b1011 9
b111010 (
1%
#620000
0%
#625000
b1100 9
b11111110101 8
b111011 (
1%
#630000
0%
#635000
b1101 9
b100000001110 8
b111100 (
1%
#640000
0%
#645000
b1110 9
b11011011101 8
b111101 (
1%
#650000
0%
#655000
b1111 9
b11111001101 8
b111110 (
1%
#660000
0%
#665000
b10000 9
b100110011110 8
b111111 (
1%
#670000
0%
#675000
b10001 9
b101000100110 8
b1000000 (
1%
#680000
0%
#685000
b10010 9
b101000111000 8
b1000001 (
1%
#690000
0%
#695000
b10011 9
b101011011010 8
b1000010 (
1%
#700000
0%
#705000
0;
11
b101100001101 0
b101100001101 :
b10100 9
b101100001010 8
b1000011 (
1%
#710000
0%
#715000
b10000 B
b10100 5
13
b111 6
b11 2
14
b1000100 (
1%
#720000
0%
#725000
1;
01
b0 8
b0 9
03
b1000101 (
1%
#730000
0%
#735000
04
b1 9
b10101000110 8
b1000110 (
1%
#740000
0%
#745000
b10 9
b1001001110 8
b1000111 (
1%
#750000
0%
#755000
b11 9
b1110100100 8
b1001000 (
1%
#760000
0%
#765000
b100 9
b1011010010 8
b1001001 (
1%
#770000
0%
#775000
b101 9
b1011111100 8
b1001010 (
1%
#780000
0%
#785000
b110 9
b100110100 8
b1001011 (
1%
#790000
0%
#795000
b111 9
b111110001 8
b1001100 (
1%
#800000
0%
#805000
b1000 9
b1111100000 8
b1001101 (
1%
#810000
0%
#815000
b1001 9
b111110000 8
b1001110 (
1%
#820000
0%
#825000
b1010 9
b110100000 8
b1001111 (
1%
#830000
0%
#835000
b1011 9
b1010000 (
1%
#840000
0%
#845000
b1100 9
b110010001 8
b1010001 (
1%
#850000
0%
#855000
b1101 9
b100001010 8
b1010010 (
1%
#860000
0%
#865000
b1110 9
b100100011 8
b1010011 (
1%
#870000
0%
#875000
b1111 9
b101010111 8
b1010100 (
1%
#880000
0%
#885000
b10000 9
b1100101000 8
b1010101 (
1%
#890000
0%
#895000
b10001 9
b10011010000 8
b1010110 (
1%
#900000
0%
#905000
b10010 9
b10100000110 8
b1010111 (
1%
#910000
0%
#915000
b10011 9
b10001011000 8
b1011000 (
1%
#920000
0%
#925000
0;
11
b10001000001 0
b10001000001 :
b10100 9
b10000111010 8
b1011001 (
1%
#930000
0%
#935000
b10000 B
b10100 5
13
b11101001 6
b100 2
14
b1011010 (
1%
#940000
0%
#945000
1;
01
b0 8
b0 9
03
b1011011 (
1%
#950000
0%
#955000
04
b1 9
b11111111111111111111100011111000 8
b1011100 (
1%
#960000
0%
#965000
b10 9
b11111111111111111111110110000000 8
b1011101 (
1%
#970000
0%
#975000
b11 9
b1000 8
b1011110 (
1%
#980000
0%
#985000
b100 9
b11111111111111111111101101000110 8
b1011111 (
1%
#990000
0%
#995000
b101 9
b11111111111111111111101010010000 8
b1100000 (
1%
#1000000
0%
#1005000
b110 9
b11111111111111111111110001111110 8
b1100001 (
1%
#1010000
0%
#1015000
b111 9
b11111111111111111111110000111111 8
b1100010 (
1%
#1020000
0%
#1025000
b1000 9
b11111111111111111111101111110010 8
b1100011 (
1%
#1030000
0%
#1035000
b1001 9
b11111111111111111111101111000010 8
b1100100 (
1%
#1040000
0%
#1045000
b1010 9
b11111111111111111111101100011000 8
b1100101 (
1%
#1050000
0%
#1055000
b1011 9
b1100110 (
1%
#1060000
0%
#1065000
b1100 9
b11111111111111111111101001110011 8
b1100111 (
1%
#1070000
0%
#1075000
b1101 9
b11111111111111111111101101000000 8
b1101000 (
1%
#1080000
0%
#1085000
b1110 9
b11111111111111111111101010111001 8
b1101001 (
1%
#1090000
0%
#1095000
b1111 9
b11111111111111111111101001100001 8
b1101010 (
1%
#1100000
0%
#1105000
b10000 9
b11111111111111111111100111011010 8
b1101011 (
1%
#1110000
0%
#1115000
b10001 9
b11111111111111111111100101001010 8
b1101100 (
1%
#1120000
0%
#1125000
b10010 9
b11111111111111111111100010101011 8
b1101101 (
1%
#1130000
0%
#1135000
b10011 9
b11111111111111111111100001011101 8
b1101110 (
1%
#1140000
0%
#1145000
0;
11
b11111111111111111111011111111110 0
b11111111111111111111011111111110 :
b10100 9
b11111111111111111111100000010101 8
b1101111 (
1%
#1150000
0%
#1155000
b10000 B
b10100 5
13
b11110101 6
b101 2
14
b1110000 (
1%
#1160000
0%
#1165000
1;
01
b0 8
b0 9
03
b1110001 (
1%
#1170000
0%
#1175000
04
b1 9
b111001011011 8
b1110010 (
1%
#1180000
0%
#1185000
b10 9
b100110101011 8
b1110011 (
1%
#1190000
0%
#1195000
b11 9
b101111101011 8
b1110100 (
1%
#1200000
0%
#1205000
b100 9
b1111100001 8
b1110101 (
1%
#1210000
0%
#1215000
b101 9
b11010011101 8
b1110110 (
1%
#1220000
0%
#1225000
b110 9
b11101101110 8
b1110111 (
1%
#1230000
0%
#1235000
b111 9
b11111011110 8
b1111000 (
1%
#1240000
0%
#1245000
b1000 9
b100111000010 8
b1111001 (
1%
#1250000
0%
#1255000
b1001 9
b101010011010 8
b1111010 (
1%
#1260000
0%
#1265000
b1010 9
b1111011 (
1%
#1270000
0%
#1275000
b1011 9
b1111100 (
1%
#1280000
0%
#1285000
b1100 9
b101010100000 8
b1111101 (
1%
#1290000
0%
#1295000
b1101 9
b101100100111 8
b1111110 (
1%
#1300000
0%
#1305000
b1110 9
b101010000111 8
b1111111 (
1%
#1310000
0%
#1315000
b1111 9
b101010000011 8
b10000000 (
1%
#1320000
0%
#1325000
b10000 9
b110001010100 8
b10000001 (
1%
#1330000
0%
#1335000
b10001 9
b110010101100 8
b10000010 (
1%
#1340000
0%
#1345000
b10010 9
b110100100001 8
b10000011 (
1%
#1350000
0%
#1355000
b10011 9
b110001001111 8
b10000100 (
1%
#1360000
0%
#1365000
0;
11
b101111110000 0
b101111110000 :
b10100 9
b101111111011 8
b10000101 (
1%
#1370000
0%
#1375000
b10000 B
b10100 5
13
b11011011 6
b110 2
14
b10000110 (
1%
#1380000
0%
#1385000
1;
01
b0 8
b0 9
03
b10000111 (
1%
#1390000
0%
#1395000
04
b1 9
b1000000011101 8
b10001000 (
1%
#1400000
0%
#1405000
b10 9
b11001101101 8
b10001001 (
1%
#1410000
0%
#1415000
b11 9
b10000011011 8
b10001010 (
1%
#1420000
0%
#1425000
b100 9
b11111111111111111111101110010011 8
b10001011 (
1%
#1430000
0%
#1435000
b101 9
b11111111111111111111100111100001 8
b10001100 (
1%
#1440000
0%
#1445000
b110 9
b11111111111111111111101101001010 8
b10001101 (
1%
#1450000
0%
#1455000
b111 9
b11111111111111111111110010110110 8
b10001110 (
1%
#1460000
0%
#1465000
b1000 9
b11111111111111111111110110111110 8
b10001111 (
1%
#1470000
0%
#1475000
b1001 9
b11111111111111111111101110001110 8
b10010000 (
1%
#1480000
0%
#1485000
b1010 9
b11111111111111111111110000111000 8
b10010001 (
1%
#1490000
0%
#1495000
b1011 9
b10010010 (
1%
#1500000
0%
#1505000
b1100 9
b11111111111111111111110010001001 8
b10010011 (
1%
#1510000
0%
#1515000
b1101 9
b11111111111111111111110101100000 8
b10010100 (
1%
#1520000
0%
#1525000
b1110 9
b11111111111111111111111000001111 8
b10010101 (
1%
#1530000
0%
#1535000
b1111 9
b11111111111111111111111000101111 8
b10010110 (
1%
#1540000
0%
#1545000
b10000 9
b11111111111111111111110000010011 8
b10010111 (
1%
#1550000
0%
#1555000
b10001 9
b11111111111111111111101101101011 8
b10011000 (
1%
#1560000
0%
#1565000
b10010 9
b11111111111111111111110000100101 8
b10011001 (
1%
#1570000
0%
#1575000
b10011 9
b11111111111111111111110011100101 8
b10011010 (
1%
#1580000
0%
#1585000
0;
11
b11111111111111111111110011000011 0
b11111111111111111111110011000011 :
b10100 9
b11111111111111111111110011101000 8
b10011011 (
1%
#1590000
0%
#1595000
b10000 B
b10100 5
13
b101 6
b111 2
14
b10011100 (
1%
#1600000
0%
#1605000
1;
01
b0 8
b0 9
03
b10011101 (
1%
#1610000
0%
#1615000
04
b1 9
b1001011000 8
b10011110 (
1%
#1620000
0%
#1625000
b10 9
b11111111111111111111101000111000 8
b10011111 (
1%
#1630000
0%
#1635000
b11 9
b11111111111111111111101000100110 8
b10100000 (
1%
#1640000
0%
#1645000
b100 9
b11111111111111111111010010010010 8
b10100001 (
1%
#1650000
0%
#1655000
b101 9
b11111111111111111111000111001000 8
b10100010 (
1%
#1660000
0%
#1665000
b110 9
b10100011 (
1%
#1670000
0%
#1675000
b111 9
b11111111111111111111000101010001 8
b10100100 (
1%
#1680000
0%
#1685000
b1000 9
b11111111111111111111001011110011 8
b10100101 (
1%
#1690000
0%
#1695000
b1001 9
b11111111111111111111001111001011 8
b10100110 (
1%
#1700000
0%
#1705000
b1010 9
b11111111111111111111001011110100 8
b10100111 (
1%
#1710000
0%
#1715000
b1011 9
b10101000 (
1%
#1720000
0%
#1725000
b1100 9
b11111111111111111111001011101110 8
b10101001 (
1%
#1730000
0%
#1735000
b1101 9
b11111111111111111111001101110000 8
b10101010 (
1%
#1740000
0%
#1745000
b1110 9
b11111111111111111111000011111111 8
b10101011 (
1%
